source_tplcentral/__init__.py
source_tplcentral/run.py
source_tplcentral/schemas/customers.json
source_tplcentral/schemas/inventory.json
source_tplcentral/schemas/items.json
source_tplcentral/schemas/orders.json
source_tplcentral/schemas/shared/common/enum/address_status_type.json
source_tplcentral/schemas/shared/common/enum/contact_type.json
source_tplcentral/schemas/shared/common/enum/fulfillment_invoicing.json
source_tplcentral/schemas/shared/common/enum/outbound_mobile_serialization_behavior.json
source_tplcentral/schemas/shared/common/enum/parcel_label_type.json
source_tplcentral/schemas/shared/common/enum/prepopulate_carrier_info.json
source_tplcentral/schemas/shared/common/enum/price_calc_field_type.json
source_tplcentral/schemas/shared/common/enum/receive_against_asns.json
source_tplcentral/schemas/shared/common/enum/serial_number_usage_level.json
source_tplcentral/schemas/shared/common/enum/transaction_confirm_invoice_create_default.json
source_tplcentral/schemas/shared/common/enum/transaction_entry_type.json
source_tplcentral/schemas/shared/common/enum/usage_level.json
source_tplcentral/schemas/shared/common/enum/warehouse_transaction_api_status.json
source_tplcentral/schemas/shared/common/enum/warehouse_transaction_source_type.json
source_tplcentral/schemas/shared/customer/models/alerts.json
source_tplcentral/schemas/shared/customer/models/asn_pre_check.json
source_tplcentral/schemas/shared/customer/models/asn_pre_check_options.json
source_tplcentral/schemas/shared/customer/models/component.json
source_tplcentral/schemas/shared/customer/models/customer_read_only.json
source_tplcentral/schemas/shared/customer/models/dimension_net.json
source_tplcentral/schemas/shared/customer/models/directed_put_away.json
source_tplcentral/schemas/shared/customer/models/edi.json
source_tplcentral/schemas/shared/customer/models/haz_mat.json
source_tplcentral/schemas/shared/customer/models/inventory_unit.json
airbyte_source_tplcentral-0.1.47.dist-info/METADATA
airbyte_source_tplcentral-0.1.47.dist-info/WHEEL
airbyte_source_tplcentral-0.1.47.dist-info/entry_points.txt
airbyte_source_tplcentral-0.1.47.dist-info/RECORD
